speedy_annotate/__init__.py
speedy_annotate/assets/conflict_screenshot.png
speedy_annotate/assets/iqa_logos/logo.icns
speedy_annotate/assets/iqa_logos/logo.pdf
speedy_annotate/assets/iqa_logos/logo.png
speedy_annotate/assets/iqa_logos/logo.svg
speedy_annotate/assets/iqa_logos/logo1x.png
speedy_annotate/assets/iqa_logos/logo2x.png
speedy_annotate/assets/iqa_logos/logo3x.png
speedy_annotate/assets/iqa_screenshot.png
speedy_annotate/assets/qc_logos/1x/black.png
speedy_annotate/assets/qc_logos/1x/blue_panel.png
speedy_annotate/assets/qc_logos/1x/grey.png
speedy_annotate/assets/qc_logos/1x/white.png
speedy_annotate/assets/qc_logos/1x/white_panel.png
speedy_annotate/assets/qc_logos/2x/black@2x.png
speedy_annotate/assets/qc_logos/2x/blue_panel@2x.png
speedy_annotate/assets/qc_logos/2x/grey@2x.png
speedy_annotate/assets/qc_logos/2x/white@2x.png
speedy_annotate/assets/qc_logos/2x/white_panel@2x.png
speedy_annotate/assets/qc_logos/3x/black@3x.png
speedy_annotate/assets/qc_logos/3x/blue_panel@3x.png
speedy_annotate/assets/qc_logos/3x/grey@3x.png
speedy_annotate/assets/qc_logos/3x/white@3x.png
speedy_annotate/assets/qc_logos/3x/white_panel@3x.png
speedy_annotate/assets/qc_logos/SVG/black.svg
speedy_annotate/assets/qc_logos/SVG/blue_panel.svg
speedy_annotate/assets/qc_logos/SVG/grey.svg
speedy_annotate/assets/qc_logos/SVG/white.svg
speedy_annotate/assets/qc_logos/SVG/white_panel.svg
speedy_annotate/assets/qc_logos/icns/white_panel.icns
speedy_annotate/assets/qc_screenshot.png
speedy_annotate/main.py
speedy_annotate/speedy_iqa/__init__.py
speedy_annotate/speedy_iqa/config.yml
speedy_annotate/speedy_iqa/graphics.py
speedy_annotate/speedy_iqa/iqa_main_app.py
speedy_annotate/speedy_iqa/iqa_wizard.py
speedy_annotate/speedy_iqa/testing_config.yml
speedy_annotate/speedy_qc/__init__.py
speedy_annotate/speedy_qc/config.yml
speedy_annotate/speedy_qc/graphics.py
speedy_annotate/speedy_qc/qc_main_app.py
speedy_annotate/speedy_qc/qc_wizard.py
speedy_annotate/utils.py
speedyannotate-1.0.9.dist-info/LICENSE
speedyannotate-1.0.9.dist-info/METADATA
speedyannotate-1.0.9.dist-info/WHEEL
speedyannotate-1.0.9.dist-info/entry_points.txt
speedyannotate-1.0.9.dist-info/RECORD
