Metadata-Version: 2.1
Name: SpeedyAnnotate
Version: 1.0.9
Summary: Tool to annotate images for machine learning
Home-page: https://gitlab.developers.cam.ac.uk/maths/cia/covid-19-projects/speedyannotate
License: MIT
Author: Ian Selby
Author-email: ias49@cam.ac.uk
Requires-Python: >=3.8
Classifier: License :: OSI Approved :: MIT License
Classifier: Programming Language :: Python :: 3
Classifier: Programming Language :: Python :: 3.8
Classifier: Programming Language :: Python :: 3.9
Classifier: Programming Language :: Python :: 3.10
Classifier: Programming Language :: Python :: 3.11
Classifier: Programming Language :: Python :: 3.12
Classifier: Programming Language :: Python :: 3.13
Requires-Dist: PyQt6 (==6.4)
Requires-Dist: PyYAML (>=6.0)
Requires-Dist: QtAwesome (>=1.2.3)
Requires-Dist: imageio (>=2.31.0)
Requires-Dist: importlib_metadata (>=6.1.0)
Requires-Dist: matplotlib (>=3.4.3)
Requires-Dist: numpy (>=1.24.2)
Requires-Dist: pandas
Requires-Dist: py2app (>=0.28.5)
Requires-Dist: pydicom (==2.3.1)
Requires-Dist: pylibjpeg (==1.4.0)
Requires-Dist: python-gdcm (>=3.0.21)
Requires-Dist: qimage2ndarray (>=1.10.0)
Requires-Dist: qt_material (>=2.14)
Requires-Dist: setuptools (>=42.0.0)
